README.md
setup.cfg
setup.py
biosamples_client.egg-info/PKG-INFO
biosamples_client.egg-info/SOURCES.txt
biosamples_client.egg-info/dependency_links.txt
biosamples_client.egg-info/requires.txt
biosamples_client.egg-info/top_level.txt
biosamples_v4/__init__.py
biosamples_v4/aap.py
biosamples_v4/api.py
biosamples_v4/convert_functions.py
biosamples_v4/encoders.py
biosamples_v4/exceptions.py
biosamples_v4/filters.py
biosamples_v4/models.py
biosamples_v4/sampletab.py
biosamples_v4/traverson.py
biosamples_v4/utilities.py